filefinder/__init__.py
filefisher/__init__.py
filefisher/_filefinder.py
filefisher/_utils.py
filefisher/cmip.py
filefisher/filters.py
filefisher/tests/__init__.py
filefisher/tests/test_cmip.py
filefisher/tests/test_filecontainer.py
filefisher/tests/test_filefinder.py
filefisher/tests/test_filefinder_fmt.py
filefisher/tests/test_filelinder_deprecation.py
filefisher/tests/test_filters.py
filefisher/tests/test_utils.py
filefisher-1.1.0.dist-info/LICENSE
filefisher-1.1.0.dist-info/METADATA
filefisher-1.1.0.dist-info/WHEEL
filefisher-1.1.0.dist-info/top_level.txt
filefisher-1.1.0.dist-info/RECORD
